schemey/__init__.py
schemey/schema.py
schemey/schema_context.py
schemey/schema_marshaller.py
schemey/schemey_format_checker.py
schemey/string_format.py
schemey/util.py
schemey/validated.py
schemey/validator.py
schemey/factory/__init__.py
schemey/factory/any_of_schema_factory.py
schemey/factory/array_schema_factory.py
schemey/factory/dataclass_schema_factory.py
schemey/factory/datetime_factory.py
schemey/factory/enum_schema_factory.py
schemey/factory/external_type_factory.py
schemey/factory/factory_schema_factory.py
schemey/factory/impl_schema_factory.py
schemey/factory/ref_schema_factory.py
schemey/factory/schema_factory_abc.py
schemey/factory/simple_type_factory.py
schemey/factory/tuple_schema_factory.py
schemey/factory/uuid_factory.py
schemey/json_schema/__init__.py
schemey/json_schema/ranges_validator.py
schemey/json_schema/schema_validator_abc.py
schemey/json_schema/timestamp_validator.py
schemey-8.0.1.dist-info/METADATA
schemey-8.0.1.dist-info/WHEEL
schemey-8.0.1.dist-info/RECORD
