Metadata-Version: 2.4
Name: schemey
Version: 8.0.1
Summary: Convention over configuration Object Schemas for python
Project-URL: Repository, https://github.com/tofarr/schemey
Author-email: Tim O'Farrell <tofarr@gmail.com>
License: MIT
Classifier: License :: OSI Approved :: MIT License
Classifier: Operating System :: OS Independent
Classifier: Programming Language :: Python :: 3
Requires-Python: >=3.10
Requires-Dist: injecty~=0.0
Requires-Dist: jsonschema~=4.8
Requires-Dist: marshy~=6.0
Provides-Extra: dev
Requires-Dist: black~=23.3; extra == 'dev'
Requires-Dist: pylint~=3.0; extra == 'dev'
Requires-Dist: pytest-cov~=4.0; extra == 'dev'
Requires-Dist: pytest-xdist~=3.2; extra == 'dev'
Requires-Dist: pytest~=7.2; extra == 'dev'
